{"assets/fonts/FiraSans-Bold.ttf":["assets/fonts/FiraSans-Bold.ttf"],"assets/fonts/FiraSans-Light.ttf":["assets/fonts/FiraSans-Light.ttf"],"assets/fonts/FiraSans-Regular.ttf":["assets/fonts/FiraSans-Regular.ttf"],"assets/fonts/Inconsolata-Bold.ttf":["assets/fonts/Inconsolata-Bold.ttf"],"assets/fonts/Inconsolata-Light.ttf":["assets/fonts/Inconsolata-Light.ttf"],"assets/fonts/Inconsolata-Medium.ttf":["assets/fonts/Inconsolata-Medium.ttf"],"assets/fonts/Inconsolata-Regular.ttf":["assets/fonts/Inconsolata-Regular.ttf"],"assets/fonts/LibreBaskerville-Bold.ttf":["assets/fonts/LibreBaskerville-Bold.ttf"],"assets/fonts/LibreBaskerville-Italic.ttf":["assets/fonts/LibreBaskerville-Italic.ttf"],"assets/fonts/LibreBaskerville-Regular.ttf":["assets/fonts/LibreBaskerville-Regular.ttf"],"assets/icons/download.svg":["assets/icons/download.svg"],"assets/icons/github.svg":["assets/icons/github.svg"],"assets/icons/linkedin.svg":["assets/icons/linkedin.svg"],"assets/images/UI%20Breaking%20News%20App.jpg":["assets/images/UI%20Breaking%20News%20App.jpg"],"assets/images/UI%20Onboarding%20Screens%20(Shop%20App).jpg":["assets/images/UI%20Onboarding%20Screens%20(Shop%20App).jpg"],"assets/images/UI%20Shop%20App.jpg":["assets/images/UI%20Shop%20App.jpg"],"assets/images/UI%20Store%20App%20(Buy%20it).jpg":["assets/images/UI%20Store%20App%20(Buy%20it).jpg"],"assets/images/UI%20Todo%20App.jpg":["assets/images/UI%20Todo%20App.jpg"],"assets/images/flutter_icon.png":["assets/images/flutter_icon.png"],"assets/images/imageSlider1.jpeg":["assets/images/imageSlider1.jpeg"],"assets/images/imageSlider2.webp":["assets/images/imageSlider2.webp"],"assets/images/imageSlider3.jpg":["assets/images/imageSlider3.jpg"],"assets/images/imageSlider4.webp":["assets/images/imageSlider4.webp"],"assets/images/imageSlider5.jpg":["assets/images/imageSlider5.jpg"],"assets/images/logoFlutter.png":["assets/images/logoFlutter.png"],"assets/json/45781-flutter.json":["assets/json/45781-flutter.json"],"assets/json/63205-flutter.json":["assets/json/63205-flutter.json"],"assets/pdf/AYMAN%20ALASWAD%20CV.pdf":["assets/pdf/AYMAN%20ALASWAD%20CV.pdf"],"packages/cupertino_icons/assets/CupertinoIcons.ttf":["packages/cupertino_icons/assets/CupertinoIcons.ttf"],"packages/flutter_rating_stars/assets/star_off.png":["packages/flutter_rating_stars/assets/star_off.png"]}